matBase/__init__.py
matBase/configs/__init__.py
matBase/configs/constants.py
matBase/configs/props.py
matBase/utils/__init__.py
matBase/utils/figure.py
matBase/utils/props.py
matprops_base-1.0.2.dist-info/LICENSE
matprops_base-1.0.2.dist-info/METADATA
matprops_base-1.0.2.dist-info/WHEEL
matprops_base-1.0.2.dist-info/top_level.txt
matprops_base-1.0.2.dist-info/RECORD
